aiokwikset/__init__.py
aiokwikset/api.py
aiokwikset/aws_kwikset.py
aiokwikset/client.py
aiokwikset/const.py
aiokwikset/device.py
aiokwikset/errors.py
aiokwikset/exceptions.py
aiokwikset/user.py
aiokwikset-0.2.1.dist-info/LICENSE
aiokwikset-0.2.1.dist-info/METADATA
aiokwikset-0.2.1.dist-info/WHEEL
aiokwikset-0.2.1.dist-info/top_level.txt
aiokwikset-0.2.1.dist-info/zip-safe
aiokwikset-0.2.1.dist-info/RECORD
