Metadata-Version: 2.1
Name: aiokwikset
Version: 0.2.1
Summary: Python interface for Kwikset Smart Locks
Home-page: https://github.com/explosivo22/aiokwikset
Author: Brad Barbour
Author-email: barbourbj@gmail.com
License: Apache Software License
Keywords: kwikset,home automation,kwikset halo,kwikset smart lock
Classifier: Programming Language :: Python :: 3
Classifier: License :: OSI Approved :: Apache Software License
Classifier: Operating System :: OS Independent
License-File: LICENSE
Requires-Dist: aiohttp (>=3.7.0)
Requires-Dist: aioboto3 (==9.4.0)
Requires-Dist: envs
Requires-Dist: python-jose
